drgpt/__init__.py
drgpt/__main__.py
drgpt/cli/__init__.py
drgpt/cli/commands.py
drgpt/cli/editor.py
drgpt/cli/interface.py
drgpt/cli/main.py
drgpt/cli/parser.py
drgpt/cli/query_handler.py
drgpt/core/__init__.py
drgpt/core/ai_interface.py
drgpt/core/config.py
drgpt/core/manager.py
drgpt/core/updater.py
drgpt/modes/__init__.py
drgpt/modes/base.py
drgpt/modes/chat.py
drgpt/modes/code.py
drgpt/modes/shell.py
drgpt/modes/standard.py
drgpt/utils/__init__.py
drgpt/utils/console.py
drgpt/utils/file_handler.py
drgpt/utils/validation.py
drgpt-2.7.2.dist-info/licenses/LICENSE
drgpt-2.7.2.dist-info/METADATA
drgpt-2.7.2.dist-info/WHEEL
drgpt-2.7.2.dist-info/entry_points.txt
drgpt-2.7.2.dist-info/top_level.txt
drgpt-2.7.2.dist-info/RECORD
